{
  "1": {
    "title": "Fashion Forecast: Predicting Next Season's Trends",
    "link": "",
    "titles": [
      {
        "title": "",
        "link": ""
      }
    ],
    "writer": "Dolly",
    "img": "https://res.cloudinary.com/dwhpe0oqy/image/upload/v1707403010/blogX/blog/kdmm7vlkqsm7mzdtguqe.jpg",
    "desc": "Get a sneak peek into upcoming fashion trends and prepare your wardrobe for the seasons ahead.",
    "category": "fashion",
    "areas": ["season"]
  },
  "2": {
    "title": "Fashion Capitals of the World: Exploring Global Style Hotspots",
    "link": "",
    "titles": [
      {
        "title": "",
        "link": ""
      }
    ],
    "writer": "Dolly",
    "img": "https://res.cloudinary.com/dwhpe0oqy/image/upload/v1707403010/blogX/blog/kdmm7vlkqsm7mzdtguqe.jpg",
    "desc": "- Embark on a virtual tour of fashion capitals around the world and discover their unique sartorial identities.",
    "category": "fashion",

    "areas": [ "travel"]
  },
  "3": {
    "title": "Fashion Faux Pas: Common Style Mistakes to Avoid",
    "link": "",
    "titles": [
      {
        "title": "",
        "link": ""
      }
    ],
    "writer": "Dolly",
    "img": "",
    "desc": " Identify and steer clear of common fashion blunders to ensure your outfits always exude polish and sophistication.",
    "category": "fashion",

    "areas": [ ""]
  },
  "4": {
    "title": "The Art of Layering: Tips for Mastering Fall and Winter Fashion",
    "link": "",
    "titles": [
      {
        "title": "",
        "link": ""
      }
    ],
    "writer": "Dolly",
    "img": "",
    "desc": "Learn layering techniques to stay warm and stylish during the colder months without sacrificing comfort.",
    "category": "fashion",

    "areas": ["season"]
  },
  "5": {
    "title": "Vintage Vibes: Incorporating Retro Fashion into Modern Looks",
    "link": "",
    "titles": [
      {
        "title": "",
        "link": ""
      }
    ],
    "writer": "Dolly",
    "img": "",
    "desc": " Embrace nostalgia and infuse your style with vintage flair by incorporating timeless pieces into contemporary outfits.",
    "category": "fashion",

    "areas": [ "design"]
  },
  "6": {
    "title": "The Intersection of Fashion and Technology: Innovations Shaping the Industry",
    "link": "",
    "titles": [
      {
        "title": "",
        "link": ""
      }
    ],
    "writer": "Dolly",
    "img": "",
    "desc": "Explore groundbreaking technological advancements revolutionizing the fashion industry, from 3D printing to virtual fashion shows.",
    "category": "fashion",

    "areas": [ ""]
  },
  "7": {
    "title": "Fashion Forecast: Predicting Next Season's Trends",
    "link": "",
    "titles": [
      {
        "title": "",
        "link": ""
      }
    ],
    "writer": "Dolly",
    "img": "",
    "desc": "Get a sneak peek into upcoming fashion trends and prepare your wardrobe for the seasons ahead.",
    "category": "fashion",

    "areas": [ "season"]
  },
  "8": {
    "title": "Wedding Season Style Guide: What to Wear for Every Wedding Event",
    "link": "",
    "titles": [
      {
        "title": "",
        "link": ""
      }
    ],
    "writer": "Dolly",
    "img": "",
    "desc": "Navigate wedding season with ease by mastering the art of dressing appropriately for various wedding-related occasions.",
    "category": "fashion",

    "areas": ["style", "season"]
  },
  "9": {
    "title": "The Art of Power Dressing: How Your Clothes Can Influence Perception",
    "link": "",
    "titles": [
      {
        "title": "",
        "link": ""
      }
    ],
    "writer": "Dolly",
    "img": "",
    "desc": "Harness the psychological power of clothing to project confidence, authority, and success in various aspects of life.",
    "category": "fashion",

    "areas": ["style", "job"]
  },
  "10": {
    "title": "Fashion on a Budget: Tips for Stylish Shopping without Breaking the Bank",
    "link": "",
    "titles": [
      {
        "title": "",
        "link": ""
      }
    ],
    "writer": "Dolly",
    "img": "",
    "desc": " Master the art of budget-friendly shopping while still maintaining a chic and fashionable wardrobe.",
    "category": "fashion",

    "areas": ["style"]
  },
  "11": {
    "title": "From Runway to Real Life: Adapting High Fashion Trends for Everyday Wear",
    "link": "",
    "titles": [
      {
        "title": "",
        "link": ""
      }
    ],
    "writer": "Dolly",
    "img": "",
    "desc": "Translate high-fashion runway looks into wearable ensembles suitable for everyday life.",
    "category": "fashion",

    "areas": [ ""]
  },
  "12": {
    "title": "Styling Tips for Petite Figures: How to Dress to Flatter Your Frame",
    "link": "",
    "titles": [
      {
        "title": "",
        "link": ""
      }
    ],
    "writer": "Dolly",
    "img": "",
    "desc": "Learn styling tricks and outfit hacks to accentuate your petite stature and create the illusion of height.",
    "category": "fashion",

    "areas": ["style"]
  },
  "13": {
    "title": "Influencer Spotlight: Fashionistas to Follow for Daily Inspiration",
    "link": "",
    "titles": [
      {
        "title": "",
        "link": ""
      }
    ],
    "writer": "Dolly",
    "img": "",
    "desc": " Discover influential fashion bloggers and Instagrammers whose style can ignite your creativity and spark new outfit ideas.",
    "category": "fashion",

    "areas": ["style"]
  },
  "14": {
    "title": "DIY Fashion Hacks: Transform Your Old Clothes into Trendy Pieces",
    "link": "",
    "titles": [
      {
        "title": "",
        "link": ""
      }
    ],
    "writer": "Dolly",
    "img": "",
    "desc": " Get creative with simple DIY techniques to revamp your wardrobe and stay on-trend without breaking the bank.",
    "category": "fashion",

    "areas": ["hacks", "creativity", "style"]
  },
  "15": {
    "title": " Guide to Dress Codes: Decoding What to Wear for Every Occasion",
    "link": "",
    "titles": [
      {
        "title": "",
        "link": ""
      }
    ],
    "writer": "Dolly",
    "img": "",
    "desc": " Navigate social and professional events with confidence by understanding and interpreting various dress codes.",
    "category": "fashion",

    "areas": ["style", "season"]
  },
  "16": {
    "title": "Celebrity Style Spotlight: Red Carpet Hits and Misses",
    "link": "",
    "titles": [
      {
        "title": "",
        "link": ""
      }
    ],
    "writer": "Dolly",
    "img": "",
    "desc": " Analyze celebrity fashion moments to glean inspiration and learn valuable style lessons. ",
    "category": "fashion",

    "areas": ["style", "Trends"]
  },
  "17": {
    "title": "Fall/Winter Fashion Trends: What's Hot This Season",
    "link": "",
    "titles": [
      {
        "title": "",
        "link": ""
      }
    ],
    "writer": "Dolly",
    "img": "",
    "desc": " Stay ahead of the curve with insights into the latest trends dominating the fall/winter fashion scene.",
    "category": "fashion",

    "areas": [ "season", "Trends"]
  },
  "18": {
    "title": "A Guide to Sustainable Fashion: How to Dress Ethically and Stylishly",
    "link": "",
    "titles": [
      {
        "title": "",
        "link": ""
      }
    ],
    "writer": "Dolly",
    "img": "",
    "desc": " Discover eco-friendly fashion choices and brands that prioritize sustainability without compromising style. ",
    "category": "fashion",

    "areas": ["style"]
  },
  "19": {
    "title": "Accessorize Like a Pro: Tips for Elevating Your Outfits",
    "link": "",
    "titles": [
      {
        "title": "",
        "link": ""
      }
    ],
    "writer": "Dolly",
    "img": "",
    "desc": "Learn how to choose the right accessories to add flair and personality to your looks. ",
    "category": "fashion",

    "areas": ["style"]
  },
  "20": {
    "title": "The Evolution of Denim: From Workwear to Runway",
    "link": "",
    "titles": [
      {
        "title": "",
        "link": ""
      }
    ],
    "writer": "Dolly",
    "img": "",
    "desc": " Trace the fascinating journey of denim through history and its impact on contemporary fashion. ",
    "category": "fashion",

    "areas": [""]
  },
  "21": {
    "title": "Hair Trends Forecast: Predicting the Next Big Hairstyle Trends",
    "link": "",
    "titles": [
      {
        "title": "",
        "link": ""
      }
    ],
    "writer": "Dolly",
    "img": "",
    "desc": "Get ahead of the curve with insights into upcoming hairstyle trends and how to incorporate them into your look.",
    "category": "fashion",

    "areas": [ "trends"]
  },
  "22": {
    "title": "Hairstyle Hacks: Clever Tricks for Perfect Hair Every Time",
    "link": "",
    "titles": [
      {
        "title": "",
        "link": ""
      }
    ],
    "writer": "Dolly",
    "img": "",
    "desc": " Discover insider hacks and shortcuts for achieving salon-worthy hairstyles at home, saving time and effort.",
    "category": "fashion",

    "areas": [ "hacks"]
  },
  "23": {
    "title": "The Best Haircuts for Thin Hair: Tips for Adding Volume and Texture",
    "link": "",
    "titles": [
      {
        "title": "",
        "link": ""
      }
    ],
    "writer": "Dolly",
    "img": "",
    "desc": " Explore flattering haircuts and styling techniques for thin hair, creating the illusion of volume and thickness.",
    "category": "fashion",

    "areas": ["style"]
  },
  "24": {
    "title": "Hairstyles for Work: Professional and Polished Looks for the Office",
    "link": "",
    "titles": [
      {
        "title": "",
        "link": ""
      }
    ],
    "writer": "Dolly",
    "img": "",
    "desc": "Elevate your professional image with polished hairstyles suitable for the workplace, combining style with sophistication.",
    "category": "fashion",

    "areas": [ "style"]
  },
  "25": {
    "title": "Cultural Hairstyles and Traditions",
    "link": "",
    "titles": [
      {
        "title": "",
        "link": ""
      }
    ],
    "writer": "Dolly",
    "img": "",
    "desc": "Draw inspiration from diverse cultural hairstyles and traditions from around the world, celebrating the beauty of global hair diversity.",
    "category": "fashion",

    "areas": [""]
  },
  "26": {
    "title": "Hair Color Dos and Don'ts: Tips for Choosing the Right Shade",
    "link": "",
    "titles": [
      {
        "title": "",
        "link": ""
      }
    ],
    "writer": "Dolly",
    "img": "",
    "desc": "Navigate the world of hair color with dos and don'ts for selecting the perfect shade to complement your skin tone and personal style.",
    "category": "fashion",

    "areas": ["style"]
  },
  "27": {
    "title": "Men's Hairstyle Trends: From Classic Cuts to Modern Looks",
    "link": "",
    "titles": [
      {
        "title": "",
        "link": ""
      }
    ],
    "writer": "Dolly",
    "img": "",
    "desc": "Stay ahead of the curve with insights into the latest trends shaping men's hairstyles, from slicked-back styles to textured crops.",
    "category": "fashion",

    "areas": ["trends"]
  },
  "28": {
    "title": "Quick and Easy Hairstyles for Busy Mornings",
    "link": "",
    "titles": [
      {
        "title": "",
        "link": ""
      }
    ],
    "writer": "Dolly",
    "img": "",
    "desc": "Streamline your morning routine with effortless hairstyles that are simple to achieve yet stylish for any occasion.",
    "category": "fashion",

    "areas": [ "style"]
  },
  "29": {
    "title": " Essential Tips for Healthy and Lustrous Looks",
    "link": "",
    "titles": [
      {
        "title": "",
        "link": ""
      }
    ],
    "writer": "Dolly",
    "img": "",
    "desc": " Dive into the fundamentals of hair care, including proper washing, conditioning, and styling techniques for maintaining healthy hair. ",
    "category": "fashion",

    "areas": [ "style"]
  },
  "30": {
    "title": "Styling Tips for Petite Figures: How to Dress to Flatter Your Frame",
    "link": "",
    "titles": [
      {
        "title": "",
        "link": ""
      }
    ],
    "writer": "Dolly",
    "img": "",
    "desc": " Learn styling tricks and outfit hacks to accentuate your petite stature and create the illusion of height.",
    "category": "fashion",

    "areas": [""]
  },"31": {
    "title": "10 Cozy Cabins for Your Winter Escape",
    "link": "",
    "titles": [
      {
        "title": "",
        "link": ""
      }
    ],
    "writer": "Dolly",
    "img": "",
    "desc": " Explore rustic and charming cabins perfect for a winter getaway, complete with crackling fireplaces and snow-covered landscapes.",
    "category": "travel",

    "areas": [""]
  },"32": {
    "title": "A Guide to Winter Camping: Tips and Tricks",
    "link": "",
    "titles": [
      {
        "title": "",
        "link": ""
      }
    ],
    "writer": "Dolly",
    "img": "",
    "desc": " Dive into the world of winter camping with this comprehensive guide, covering gear, safety, and the best destinations for snowy adventures.",
    "category": "travel",

    "areas": [""]
  },"33": {
    "title": "Chasing Northern Lights: The Ultimate Bucket List Experience",
    "link": "",
    "titles": [
      {
        "title": "",
        "link": ""
      }
    ],
    "writer": "Dolly",
    "img": "",
    "desc": "Discover the best places around the world to witness the mesmerizing Northern Lights and tips for increasing your chances of seeing them.",
    "category": "travel",

    "areas": [""]
  },"34": {
    "title": "Skiing 101: A Beginner's Guide to Hitting the Slopes",
    "link": "",
    "titles": [
      {
        "title": "",
        "link": ""
      }
    ],
    "writer": "Dolly",
    "img": "",
    "desc": " Get ready to hit the slopes with this beginner's guide to skiing, covering everything from choosing the right equipment to mastering the basics.",
    "category": "travel",

    "areas": [""]
  },"35": {
    "title": "Warm Winter Destinations for Sun Seekers",
    "link": "",
    "titles": [
      {
        "title": "",
        "link": ""
      }
    ],
    "writer": "Dolly",
    "img": "",
    "desc": "Escape the cold and discover warm winter destinations perfect for beach lovers, including tropical islands and sunny coastal towns.",
    "category": "travel",

    "areas": [""]
  },"36": {
    "title": "The Best Hot Springs to Soak in During Winter",
    "link": "",
    "titles": [
      {
        "title": "",
        "link": ""
      }
    ],
    "writer": "Dolly",
    "img": "",
    "desc": " Unwind and relax in natural hot springs surrounded by snow-covered landscapes, offering the perfect remedy for winter blues.",
    "category": "travel",

    "areas": [""]
  },"37": {
    "title": "Winter Wildlife Watching: Where to Spot Animals in the Snow",
    "link": "",
    "titles": [
      {
        "title": "",
        "link": ""
      }
    ],
    "writer": "Dolly",
    "img": "",
    "desc": " Embark on a wildlife adventure and discover the best destinations for spotting animals in their winter habitats, from polar bears in Canada to penguins in Antarctica.",
    "category": "travel",

    "areas": [""]
  },"38": {
    "title": "Winter Adventure Activities for Thrill Seekers",
    "link": "",
    "titles": [
      {
        "title": "",
        "link": ""
      }
    ],
    "writer": "Dolly",
    "img": "",
    "desc": " Get your adrenaline pumping with winter adventure activities like snowmobiling, ice climbing, and dog sledding in breathtaking destinations.",
    "category": "travel",

    "areas": [""]
  },"39": {
    "title": "The Ultimate Guide to Winter Road Trips",
    "link": "",
    "titles": [
      {
        "title": "",
        "link": ""
      }
    ],
    "writer": "Dolly",
    "img": "",
    "desc": " Hit the road and embark on a winter road trip adventure, discovering scenic routes, charming towns, and hidden gems along the way.",
    "category": "travel",

    "areas": [""]
  },"40": {
    "title": "Snowy City Escapes: Urban Adventures in Winter",
    "link": "",
    "titles": [
      {
        "title": "",
        "link": ""
      }
    ],
    "writer": "Dolly",
    "img": "",
    "desc": " Experience the charm of cities blanketed in snow with this guide to winter city escapes, featuring festive decorations, ice skating rinks, and cozy cafes.",
    "category": "travel",

    "areas": [""]
  },"41": {
    "title": "Winter Photography Tips: Capturing the Beauty of the Season",
    "link": "",
    "titles": [
      {
        "title": "",
        "link": ""
      }
    ],
    "writer": "Dolly",
    "img": "",
    "desc": "- Elevate your winter photography skills with these expert tips for capturing stunning landscapes, snowflakes, and frosty scenes.",
    "category": "travel",

    "areas": [""]
  },"42": {
    "title": "The Best Food and Drink Festivals of Winter",
    "link": "",
    "titles": [
      {
        "title": "",
        "link": ""
      }
    ],
    "writer": "Dolly",
    "img": "",
    "desc": "Indulge in delicious food and drink festivals around the world, showcasing seasonal specialties and culinary delights.",
    "category": "travel",

    "areas": ["food","season"]
  },"43": {
    "title": "Eco-Friendly Winter Travel: Tips for Sustainable Adventures",
    "link": "",
    "titles": [
      {
        "title": "",
        "link": ""
      }
    ],
    "writer": "Dolly",
    "img": "",
    "desc": "Reduce your carbon footprint and travel responsibly with these eco-friendly tips for winter adventures, including green accommodations and carbon offset programs.",
    "category": "travel",

    "areas": [""]
  },
  "44": {
    "title": "Family-Friendly Winter Destinations: Fun for All Ages",
    "link": "",
    "titles": [
      {
        "title": "",
        "link": ""
      }
    ],
    "writer": "Dolly",
    "img": "",
    "desc": "Plan the perfect family winter getaway with activities like sledding, ice skating, and building snowmen in kid-friendly destinations.",
    "category": "travel",

    "areas": [""]
  }, "45": {
    "title": "Winter Wellness Activities: Embracing Hygge and Self-Care",
    "link": "",
    "titles": [
      {
        "title": "",
        "link": ""
      }
    ],
    "writer": "Dolly",
    "img": "",
    "desc": " Embrace the Danish concept of hygge and prioritize self-care with winter wellness activities like cozying up with a good ",
    "category": "travel",

    "areas": [""]
  }, "46": {
    "title": "Snowy Spa Retreats: Relaxation in Winter Wonderland",
    "link": "",
    "titles": [
      {
        "title": "",
        "link": ""
      }
    ],
    "writer": "Dolly",
    "img": "",
    "desc": "Treat yourself to a luxurious spa retreat surrounded by snow-covered mountains, offering massages, facials, and thermal baths.",
    "category": "season",

    "areas": ["beauty"]
  }, "47": {
    "title": "Beach Essentials: What to Pack for a Summer Getaway",
    "link": "",
    "titles": [
      {
        "title": "",
        "link": ""
      }
    ],
    "writer": "Dolly",
    "img": "",
    "desc": "Pack your beach bag like a pro with this guide to essential items for a fun and relaxing beach vacation.",
    "category": "packing",

    "areas": [""]
  }, "48": {
    "title": "City Explorations: Packing Light for Urban Summer Travel",
    "link": "",
    "titles": [
      {
        "title": "",
        "link": ""
      }
    ],
    "writer": "Dolly",
    "img": "",
    "desc": "Explore cities comfortably with tips on packing light and essentials for navigating bustling streets and attractions.",
    "category": "packing",

    "areas": [""]
  }, "49": {
    "title": "Camping in Style: Packing Tips for Summer Outdoor Adventures",
    "link": "",
    "titles": [
      {
        "title": "",
        "link": ""
      }
    ],
    "writer": "Dolly",
    "img": "",
    "desc": " Enjoy the great outdoors in comfort with essential packing tips for camping gear, clothing, and supplies.",
    "category": "packing",

    "areas": [""]
  }, "50": {
    "title": "Cruise Essentials: What to Pack for a Summer Sailing",
    "link": "",
    "titles": [
      {
        "title": "",
        "link": ""
      }
    ],
    "writer": "Dolly",
    "img": "",
    "desc": "Set sail with confidence by packing wisely for your summer cruise, including clothing for various occasions and onboard essentials.",
    "category": "packing",

    "areas": [""]
  }, "51": {
    "title": "Hiking Essentials: Packing Tips for Summer Trails",
    "link": "",
    "titles": [
      {
        "title": "",
        "link": ""
      }
    ],
    "writer": "Dolly",
    "img": "",
    "desc": "Prepare for summer hikes with this guide to essential gear, clothing, and snacks for staying safe and comfortable on the trails.",
    "category": "packing",

    "areas": [""]
  }, "52": {
    "title": "Solo Travel Packing Guide: Tips for Summer Adventures",
    "link": "",
    "titles": [
      {
        "title": "",
        "link": ""
      }
    ],
    "writer": "Dolly",
    "img": "",
    "desc": "Travel solo with ease by packing efficiently and essentials for staying safe and organized during your summer adventures.",
    "category": "packing",

    "areas": [""]
  }, "53": {
    "title": "Family Vacation Packing Tips: Essentials for Summer Travel with Kids",
    "link": "",
    "titles": [
      {
        "title": "",
        "link": ""
      }
    ],
    "writer": "Dolly",
    "img": "",
    "desc": " Keep the whole family happy and organized with tips for packing essentials and entertainment for summer vacations.",
    "category": "packing",

    "areas": ["travel"]
  }, "54": {
    "title": "Adventure Travel Packing Guide: Essentials for Summer Thrills",
    "link": "",
    "titles": [
      {
        "title": "",
        "link": ""
      }
    ],
    "writer": "Dolly",
    "img": "",
    "desc": "Gear up for adrenaline-pumping adventures with essential packing tips for outdoor activities like zip-lining, rafting, and rock climbing.",
    "category": "packing",

    "areas": ["travel"]
  }, "55": {
    "title": "Beach Day Bag Essentials: Packing Tips for Summer Fun",
    "link": "",
    "titles": [
      {
        "title": "",
        "link": ""
      }
    ],
    "writer": "Dolly",
    "img": "",
    "desc": "Pack your beach bag like a pro with essentials for sun protection, hydration, and entertainment for a day of seaside relaxation.",
    "category": "packing",

    "areas": ["travel"]
  }, "56": {
    "title": "International Travel Packing Tips: Essentials for Summer Jet Setting",
    "link": "",
    "titles": [
      {
        "title": "",
        "link": ""
      }
    ],
    "writer": "Dolly",
    "img": "",
    "desc": "Navigate international travel with ease by packing essentials, including travel documents, currency, and adaptors for electronic devices.",
    "category": "travel",

    "areas": ["packing"]
  }, "57": {
    "title": "Staycation Packing Guide: Essentials for Summer Stay-at-Home Fun",
    "link": "",
    "titles": [
      {
        "title": "",
        "link": ""
      }
    ],
    "writer": "Dolly",
    "img": "",
    "desc": "Enjoy a relaxing staycation with tips for packing essentials and creating a vacation-like atmosphere at home.",
    "category": "travel",

    "areas": ["packing"]
  }, "58": {
    "title": "Picnic Essentials: Packing Tips for Summer Outdoor Dining",
    "link": "",
    "titles": [
      {
        "title": "",
        "link": ""
      }
    ],
    "writer": "Dolly",
    "img": "",
    "desc": " Enjoy alfresco dining with tips for packing essentials like portable snacks, drinks, and picnic blankets for a memorable summer picnic.",
    "category": "travel",

    "areas": ["packing"]
  }, "59": {
    "title": "Romantic Getaway Packing Tips: Essentials for Summer Love",
    "link": "",
    "titles": [
      {
        "title": "",
        "link": ""
      }
    ],
    "writer": "Dolly",
    "img": "",
    "desc": " Plan a romantic escape with tips for packing essentials like candles, massage oils, and special treats for a memorable summer getaway.",
    "category": "travel",

    "areas": ["packing"]
  }, "60": {
    "title": "Foodie Travel Packing Guide: Essentials for Summer Gastronomy",
    "link": "",
    "titles": [
      {
        "title": "",
        "link": ""
      }
    ],
    "writer": "Dolly",
    "img": "",
    "desc": "Explore culinary delights with tips for packing foodie essentials like restaurant guides, cooking utensils, and food journals for summer food adventures.",
    "category": "travel",

    "areas": ["packing"]
  }, "61": {
    "title": "",
    "link": "",
    "titles": [
      {
        "title": "",
        "link": ""
      }
    ],
    "writer": "Dolly",
    "img": "",
    "desc": "",
    "category": "",

    "areas": [""]
  }, "44": {
    "title": "",
    "link": "",
    "titles": [
      {
        "title": "",
        "link": ""
      }
    ],
    "writer": "Dolly",
    "img": "",
    "desc": "",
    "category": "",

    "areas": [""]
  }, "44": {
    "title": "",
    "link": "",
    "titles": [
      {
        "title": "",
        "link": ""
      }
    ],
    "writer": "Dolly",
    "img": "",
    "desc": "",
    "category": "",

    "areas": [""]
  }, "44": {
    "title": "",
    "link": "",
    "titles": [
      {
        "title": "",
        "link": ""
      }
    ],
    "writer": "Dolly",
    "img": "",
    "desc": "",
    "category": "",

    "areas": [""]
  }, "44": {
    "title": "",
    "link": "",
    "titles": [
      {
        "title": "",
        "link": ""
      }
    ],
    "writer": "Dolly",
    "img": "",
    "desc": "",
    "category": "",

    "areas": [""]
  }, "44": {
    "title": "",
    "link": "",
    "titles": [
      {
        "title": "",
        "link": ""
      }
    ],
    "writer": "Dolly",
    "img": "",
    "desc": "",
    "category": "",

    "areas": [""]
  }, "44": {
    "title": "",
    "link": "",
    "titles": [
      {
        "title": "",
        "link": ""
      }
    ],
    "writer": "Dolly",
    "img": "",
    "desc": "",
    "category": "",

    "areas": [""]
  }, "44": {
    "title": "",
    "link": "",
    "titles": [
      {
        "title": "",
        "link": ""
      }
    ],
    "writer": "Dolly",
    "img": "",
    "desc": "",
    "category": "",

    "areas": [""]
  }, "44": {
    "title": "",
    "link": "",
    "titles": [
      {
        "title": "",
        "link": ""
      }
    ],
    "writer": "Dolly",
    "img": "",
    "desc": "",
    "category": "",

    "areas": [""]
  }, "44": {
    "title": "",
    "link": "",
    "titles": [
      {
        "title": "",
        "link": ""
      }
    ],
    "writer": "Dolly",
    "img": "",
    "desc": "",
    "category": "",

    "areas": [""]
  }, "44": {
    "title": "",
    "link": "",
    "titles": [
      {
        "title": "",
        "link": ""
      }
    ],
    "writer": "Dolly",
    "img": "",
    "desc": "",
    "category": "",

    "areas": [""]
  }, "44": {
    "title": "",
    "link": "",
    "titles": [
      {
        "title": "",
        "link": ""
      }
    ],
    "writer": "Dolly",
    "img": "",
    "desc": "",
    "category": "",

    "areas": [""]
  }, "44": {
    "title": "",
    "link": "",
    "titles": [
      {
        "title": "",
        "link": ""
      }
    ],
    "writer": "Dolly",
    "img": "",
    "desc": "",
    "category": "",

    "areas": [""]
  }, "44": {
    "title": "",
    "link": "",
    "titles": [
      {
        "title": "",
        "link": ""
      }
    ],
    "writer": "Dolly",
    "img": "",
    "desc": "",
    "category": "",

    "areas": [""]
  }, "44": {
    "title": "",
    "link": "",
    "titles": [
      {
        "title": "",
        "link": ""
      }
    ],
    "writer": "Dolly",
    "img": "",
    "desc": "",
    "category": "",

    "areas": [""]
  }, "44": {
    "title": "",
    "link": "",
    "titles": [
      {
        "title": "",
        "link": ""
      }
    ],
    "writer": "Dolly",
    "img": "",
    "desc": "",
    "category": "",

    "areas": [""]
  }, "44": {
    "title": "",
    "link": "",
    "titles": [
      {
        "title": "",
        "link": ""
      }
    ],
    "writer": "Dolly",
    "img": "",
    "desc": "",
    "category": "",

    "areas": [""]
  },
 
  "36": {
    "title": "Surviving Winter Travel: Essential Tips for Cold-Weather Adventures",
    "desc": "Discover essential tips and tricks for navigating winter travel safely and comfortably, from packing the right gear to staying warm in chilly climates. Whether you're hitting the slopes or exploring snowy landscapes, these winter travel hacks will ensure a memorable and enjoyable journey.",
    "areas": ["Travel", "Winter", "Adventure"]
  },
  "37": {
    "title": "Winter Photography Guide: Capturing the Beauty of the Season",
    "desc": "Unlock the secrets to stunning winter photography with expert tips on lighting, composition, and capturing the unique beauty of snowy landscapes. Whether you're a seasoned photographer or a beginner, this guide will help you create captivating winter imagery.",
    "areas": ["Photography", "Winter", "Outdoor"]
  },
  "38": {
    "title": "Cozy Cabin Retreats: Embracing Hygge in Winter Escapes",
    "desc": "Escape the winter chill and embrace the cozy comforts of cabin life with this guide to the best cabin retreats around the world. From rustic mountain hideaways to lakeside lodges, discover your perfect hygge-filled winter escape.",
    "areas": ["Travel", "Winter", "Hygge"]
  },
  "39": {
    "title": "Winter Wildlife Adventures: Exploring Arctic Habitats and Beyond",
    "desc": "Embark on a winter wildlife adventure and encounter majestic creatures in their natural habitats. From polar bears in the Arctic to penguins in Antarctica, discover the wonders of winter wildlife around the globe.",
    "areas": ["Travel", "Winter", "Wildlife"]
  },
  "40": {
    "title": "The Magic of Christmas Markets: Festive Delights Around the World",
    "desc": "Immerse yourself in the festive spirit and explore the enchanting world of Christmas markets. From Europe's traditional markets to North America's winter wonderlands, discover the magic of the holiday season.",
    "areas": ["Travel", "Winter", "Christmas"]
  },
  "41": {
    "title": "Winter Wellness Retreats: Rejuvenating Mind, Body, and Soul",
    "desc": "Escape the winter blues and rejuvenate your mind, body, and soul with a wellness retreat. From yoga retreats in tropical paradises to spa getaways in snowy mountains, discover the perfect winter wellness escape.",
    "areas": ["Travel", "Winter", "Wellness"]
  },
  "42": {
    "title": "Epic Snowboarding Destinations: Shredding Powder Around the World",
    "desc": "Calling all snowboarders! Explore epic snowboarding destinations around the world, from world-class resorts to off-the-beaten-path powder havens. Get ready to carve up the slopes and experience the ultimate winter adventure.",
    "areas": ["Travel", "Winter", "Snowboarding"]
  },
  "43": {
    "title": "Winter Camping 101: Tips for Cold-Weather Camping Adventures",
    "desc": "Brave the elements and embark on a winter camping adventure with confidence. From choosing the right gear to staying warm in sub-zero temperatures, this guide has everything you need to know for a successful cold-weather camping trip.",
    "areas": ["Travel", "Winter", "Camping"]
  },
  "44": {
    "title": "Chasing Frozen Waterfalls: Winter Adventures in Search of Ice",
    "desc": "Experience the breathtaking beauty of frozen waterfalls and embark on a winter adventure in search of icy wonders. From cascading ice curtains to towering ice formations, discover the world's most stunning frozen waterfalls.",
    "areas": ["Travel", "Winter", "Adventure"]
  },
  "45": {
    "title": "Arctic Cruises: Exploring Polar Wonders in Winter",
    "desc": "Set sail for the Arctic and embark on a once-in-a-lifetime cruise adventure. From spotting polar bears on pack ice to witnessing the mesmerizing beauty of the Northern Lights, discover the magic of winter in the Arctic.",
    "areas": ["Travel", "Winter", "Cruise"]
  },
  "46": {
    "title": "Winter Road Trips: Scenic Drives Through Snow-Covered Landscapes",
    "desc": "Hit the road and embark on a winter road trip adventure through snow-covered landscapes. From winding mountain roads to coastal highways, discover the most scenic routes for winter driving.",
    "areas": ["Travel", "Winter", "Road Trip"]
  },
  "47": {
    "title": "Exploring Winter Waterways: Kayaking and Canoeing Adventures",
    "desc": "Paddle through winter wonderlands and embark on kayaking and canoeing adventures in colder climates. From tranquil lakes to frozen rivers, discover the magic of winter waterways.",
    "areas": ["Travel", "Winter", "Adventure"]
  },
  "48": {
    "title": "Winter Glamping Getaways: Luxurious Camping Escapes in the Snow",
    "desc": "Experience the best of winter camping without sacrificing comfort with a glamping getaway. From cozy yurts to luxurious cabins, discover the most luxurious winter glamping destinations around the world.",
    "areas": ["Travel", "Winter", "Glamping"]
  },
  "49": {
    "title": "Winter Mountain Biking: Thrilling Trails for Cold-Weather Riding",
    "desc": "Gear up and hit the trails for some exhilarating winter mountain biking adventures. From snowy singletracks to icy downhill descents, discover the best cold-weather trails for winter riding.",
    "areas": ["Travel", "Winter", "Mountain Biking"]
  },
  "50": {
    "title": "Winter Beach Escapes: Sunny Destinations for Warm-Weather Getaways",
    "desc": "Escape the winter chill and soak up the sun on a winter beach escape. From tropical paradises to exotic islands, discover the best warm-weather destinations for a winter getaway.",
    "areas": ["Travel", "Winter", "Beach"]
  },
  "51": {
    "title": "Winter Family Fun: Kid-Friendly Activities for Cold-Weather Adventures",
    "desc": "Plan the perfect winter family getaway with these kid-friendly activities for cold-weather adventures. From sledding and ice skating to building snowmen, there's something for everyone to enjoy in the snow.",
    "areas": ["Travel", "Winter", "Family"]
  },
  "52": {
    "title": "Winter Horseback Riding: Exploring Snow-Covered Trails on Horseback",
    "desc": "Saddle up and explore snow-covered landscapes on horseback with these winter horseback riding adventures. From scenic trail rides to multi-day treks, discover the magic of winter from the back of a horse.",
    "areas": ["Travel", "Winter", "Adventure"]
  },
  "54": {
    "title": "Winter Wildlife Photography: Capturing Arctic Fauna in Their Element",
    "desc": "Embark on a photographic journey through the winter wonderland of the Arctic and capture stunning images of polar bears, arctic foxes, and other iconic wildlife species in their natural habitat.",
    "areas": ["Travel", "Winter", "Photography"]
  },
  "55": {
    "title": "Ice Climbing Adventures: Conquering Frozen Cascades and Glaciers",
    "desc": "Gear up and tackle frozen waterfalls, towering ice formations, and sheer ice walls with these exhilarating ice climbing adventures in some of the world's most spectacular winter landscapes.",
    "areas": ["Travel", "Winter", "Adventure"]
  },
  "56": {
    "title": "Winter Spa Retreats: Relaxing Getaways for Pampering and Wellness",
    "desc": "Indulge in relaxation and rejuvenation with a winter spa retreat. From hot stone massages to thermal baths, treat yourself to luxurious pampering amidst the serene beauty of snow-covered landscapes.",
    "areas": ["Travel", "Winter", "Wellness"]
  },
  "57": {
    "title": "Winter Camping Cuisine: Delicious Recipes for Cold-Weather Cooking",
    "desc": "Elevate your winter camping experience with delicious and hearty recipes designed for cooking in cold weather. From hearty stews to warming drinks, these recipes will keep you fueled and satisfied during your outdoor adventures.",
    "areas": ["Travel", "Winter", "Camping"]
  },
  "58": {
    "title": "Winter Astronomy: Stargazing and Northern Lights Viewing",
    "desc": "Discover the wonders of the night sky during the winter months with these stellar stargazing and Northern Lights viewing experiences. From remote observatories to secluded wilderness locations, marvel at the beauty of the cosmos.",
    "areas": ["Travel", "Winter", "Adventure"]
  },
  "59": {
    "title": "Winter Volunteering: Giving Back Through Cold-Weather Community Service",
    "desc": "Make a difference and give back to communities in need through winter volunteering opportunities. From helping with snow removal to volunteering at homeless shelters, discover meaningful ways to contribute during the cold months.",
    "areas": ["Travel", "Winter", "Community"]
  },
  "60": {
    "title": "Winter Archaeology: Exploring Ancient Sites in the Snow",
    "desc": "Embark on a journey through time and explore ancient sites and archaeological wonders in the snow. From ancient ruins to prehistoric caves, discover the rich history and cultural heritage preserved in winter landscapes.",
    "areas": ["Travel", "Winter", "Adventure"]
  },
  "61": {
    "title": "Winter Horse-Drawn Sleigh Rides: Romantic Escapes in Snowy Settings",
    "desc": "Experience the romance of winter with a horse-drawn sleigh ride through snowy landscapes. Snuggle up under blankets and enjoy the enchanting scenery as you glide through winter wonderlands.",
    "areas": ["Travel", "Winter", "Romance"]
  },
  "62": {
    "title": "Winter Birdwatching: Spotting Avian Wonders in Cold-Weather Habitats",
    "desc": "Embark on a birdwatching adventure and discover the diverse array of bird species that inhabit cold-weather habitats during the winter months. From snow buntings to bald eagles, observe avian wonders in their natural environment.",
    "areas": ["Travel", "Winter", "Wildlife"]
  },
  "63": {
    "title": "Winter Running: Tips for Cold-Weather Jogging and Trail Running",
    "desc": "Stay active and embrace the chill with winter running tips for cold-weather jogging and trail running. From layering techniques to winter running gear, conquer the elements and enjoy the beauty of snowy landscapes on foot.",
    "areas": ["Travel", "Winter", "Fitness"]
  },
  "64": {
    "title": "Winter Music Festivals: Enjoying Live Music in Snowy Settings",
    "desc": "Groove to the beat and enjoy live music in snowy settings with these winter music festivals. From outdoor concerts to cozy indoor venues, discover the best festivals for music lovers to enjoy in the cold.",
    "areas": ["Travel", "Winter", "Music"]
  },
  "65": {
    "title": "Winter Astronomy: Stargazing and Northern Lights Viewing",
    "desc": "Discover the wonders of the night sky during the winter months with these stellar stargazing and Northern Lights viewing experiences. From remote observatories to secluded wilderness locations, marvel at the beauty of the cosmos.",
    "areas": ["Travel", "Winter", "Adventure"]
  },
  "66": {
    "title": "Winter Volunteering: Giving Back Through Cold-Weather Community Service",
    "desc": "Make a difference and give back to communities in need through winter volunteering opportunities. From helping with snow removal to volunteering at homeless shelters, discover meaningful ways to contribute during the cold months.",
    "areas": ["Travel", "Winter", "Community"]
  },
  "67": {
    "title": "Winter Archaeology: Exploring Ancient Sites in the Snow",
    "desc": "Embark on a journey through time and explore ancient sites and archaeological wonders in the snow. From ancient ruins to prehistoric caves, discover the rich history and cultural heritage preserved in winter landscapes.",
    "areas": ["Travel", "Winter", "Adventure"]
  },
  "68": {
    "title": "Winter Horse-Drawn Sleigh Rides: Romantic Escapes in Snowy Settings",
    "desc": "Experience the romance of winter with a horse-drawn sleigh ride through snowy landscapes. Snuggle up under blankets and enjoy the enchanting scenery as you glide through winter wonderlands.",
    "areas": ["Travel", "Winter", "Romance"]
  },
  "69": {
    "title": "Winter Birdwatching: Spotting Avian Wonders in Cold-Weather Habitats",
    "desc": "Embark on a birdwatching adventure and discover the diverse array of bird species that inhabit cold-weather habitats during the winter months. From snow buntings to bald eagles, observe avian wonders in their natural environment.",
    "areas": ["Travel", "Winter", "Wildlife"]
  },
  "70": {
    "title": "Winter Running: Tips for Cold-Weather Jogging and Trail Running",
    "desc": "Stay active and embrace the chill with winter running tips for cold-weather jogging and trail running. From layering techniques to winter running gear, conquer the elements and enjoy the beauty of snowy landscapes on foot.",
    "areas": ["Travel", "Winter", "Fitness"]
  },
  "71": {
    "title": "Winter Music Festivals: Enjoying Live Music in Snowy Settings",
    "desc": "Groove to the beat and enjoy live music in snowy settings with these winter music festivals. From outdoor concerts to cozy indoor venues, discover the best festivals for music lovers to enjoy in the cold.",
    "areas": ["Travel", "Winter", "Music"]
  }
}

  
 [
  {
    "title": "Fashion Forecast: Predicting Next Season's Trends",
    "link": "",
    "titles": [
      {
        "title": "Fashion Capitals of the World: Exploring Global Style Hotspots",
        "link": ""
      },
      {
        "title": "Fashion Faux Pas: Common Style Mistakes to Avoid",
        "link": ""
      },
      {
        "title": "The Art of Layering: Tips for Mastering Fall and Winter Fashion",
        "link": ""
      },
      {
        "title": "Vintage Vibes: Incorporating Retro Fashion into Modern Looks",
        "link": ""
      },
      {
        "title": "The Intersection of Fashion and Technology: Innovations Shaping the Industry",
        "link": ""
      },
      {
        "title": "Fashion Forecast: Predicting Next Season's Trends",
        "link": ""
      }
    ],
    "writer": "",
    "img": "",
    "desc": "Get a sneak peek into upcoming fashion trends and prepare your wardrobe for the seasons ahead.",
    "areas": ["fashion", "season"],
    "areas": ["style", "accessories", "trends", "forecast"] // Additional areas included
  },
  
 ]
 [
  {
    title: "Fashion Forecast: Predicting Next Season's Trends",
    link: "",
    titles: [
      {
        title: "",
        link: "",
      },
    ],
    writer: "Dolly",
    img: "",
    desc: "Get a sneak peek into upcoming fashion trends and prepare your wardrobe for the seasons ahead.",
    category: "fashion",
    areas: ["season"],
  },
];
